fp/__init__.py
fp/cartesian/__init__.py
fp/cartesian/arrow.py
fp/cartesian/either.py
fp/cartesian/hom.py
fp/cartesian/prod.py
fp/instances/__init__.py
fp/instances/algebra.py
fp/instances/lifts.py
fp/instances/list.py
fp/instances/num.py
fp/instances/state.py
fp/instances/str.py
fp/instances/struct.py
fp/instances/tensor_mod.py
fp/instances/wrap.py
fp/io/__init__.py
fp/io/asserts.py
fp/io/cast.py
fp/io/checks.py
fp/io/docs.py
fp/io/exceptions.py
fp/io/log.py
fp/io/show.py
fp/meta/__init__.py
fp/meta/constructor.py
fp/meta/functor.py
fp/meta/kind.py
fp/meta/method.py
fp/meta/monad.py
fp/meta/type.py
fp/tensors/__init__.py
fp/tensors/backend/__init__.py
fp/tensors/backend/_pkgs.py
fp/tensors/backend/interfaces.py
fp/tensors/backend/wrap_alg.py
fp/tensors/impl.py
fp/tensors/shape.py
fp/tensors/tens.py
fp/tensors/tensor.py
fp/tensors/tensor_base.py
fp/tensors/typed_tensor.py
fp/utils/__init__.py
fp/utils/cache.py
funprogram-0.9.2.dist-info/LICENSE.md
funprogram-0.9.2.dist-info/METADATA
funprogram-0.9.2.dist-info/WHEEL
funprogram-0.9.2.dist-info/entry_points.txt
funprogram-0.9.2.dist-info/RECORD
