Metadata-Version: 2.1
Name: funprogram
Version: 0.9.2
Summary: A functional programming framework for python.
License: MIT
Author: Olivier Peltre
Author-email: opeltre@gmail.com
Requires-Python: >=3.11,<4.0
Classifier: License :: OSI Approved :: MIT License
Classifier: Programming Language :: Python :: 3
Classifier: Programming Language :: Python :: 3.11
Classifier: Programming Language :: Python :: 3.12
Provides-Extra: jax
Requires-Dist: colorama (>=0.4.6,<0.5.0)
Requires-Dist: jax (>=0.4,<0.5) ; extra == "jax"
Requires-Dist: numpy (>=1.26,<2.0)
Requires-Dist: poethepoet
